streamer_binaries/__init__.py
streamer_binaries/ffmpeg-linux-arm64
streamer_binaries/ffmpeg-linux-arm64-ubuntu-22.04
streamer_binaries/ffmpeg-linux-arm64-ubuntu-24.04
streamer_binaries/ffprobe-linux-arm64
streamer_binaries/packager-linux-arm64
shaka_streamer_binaries-1.2.1.dist-info/METADATA
shaka_streamer_binaries-1.2.1.dist-info/WHEEL
shaka_streamer_binaries-1.2.1.dist-info/top_level.txt
shaka_streamer_binaries-1.2.1.dist-info/RECORD
