Metadata-Version: 2.2
Name: shaka-streamer-binaries
Version: 1.2.1
Summary: A package containing FFmpeg, FFprobe, and Shaka Packager static builds.
Home-page: https://github.com/shaka-project/shaka-streamer/tree/main/binaries
Author: Google
Classifier: Programming Language :: Python :: 3
Classifier: License :: OSI Approved :: Apache Software License
Classifier: Operating System :: POSIX :: Linux
Classifier: Operating System :: MacOS :: MacOS X
Classifier: Operating System :: Microsoft :: Windows
Requires-Dist: distro<2,>=1.9; platform_system == "Linux"
Dynamic: author
Dynamic: classifier
Dynamic: description
Dynamic: description-content-type
Dynamic: home-page
Dynamic: requires-dist
Dynamic: summary
